<!--Copyright 2012 MLB Advanced Media, L.P.  Use of any content on this page acknowledges agreement to the terms posted here http://gdx.mlb.com/components/copyright.txt--><inning num="4" away_team="oak" home_team="sea" next="Y"><top><atbat num="28" b="1" s="1" o="1" start_tfs="161108" start_tfs_zulu="2012-03-03T21:11:08Z" batter="518626" stand="R" b_height="6-0" pitcher="119154" p_throws="R" des="Josh Donaldson flies out to right fielder Ichiro Suzuki.  " event="Flyout"><pitch des="Called Strike" id="242" type="S" tfs="161126" tfs_zulu="2012-03-03T21:11:26Z" x="55.79" y="145.92" sv_id="120303_141125" start_speed="88.0" end_speed="80.9" sz_top="3.22" sz_bot="1.34" pfx_x="-2.1" pfx_z="7.58" px="1.382" pz="2.651" x0="-1.926" y0="50.0" z0="6.487" vx0="9.074" vy0="-128.555" vz0="-5.879" ax="-3.509" ay="27.643" az="-19.463" break_y="23.8" break_angle="4.6" break_length="5.1" pitch_type="FC" type_confidence=".889" zone="12" spin_dir="195.431" spin_rate="1488.132"  cc="" mt=""/><pitch des="Ball" id="243" type="B" tfs="161143" tfs_zulu="2012-03-03T21:11:43Z" x="41.20" y="153.69" sv_id="120303_141142" start_speed="89.1" end_speed="81.6" sz_top="3.12" sz_bot="1.36" pfx_x="-4.88" pfx_z="8.46" px="1.823" pz="2.112" x0="-1.866" y0="50.0" z0="6.377" vx0="11.058" vy0="-130.025" vz0="-7.444" ax="-8.284" ay="29.297" az="-17.741" break_y="23.8" break_angle="17.0" break_length="4.8" pitch_type="FF" type_confidence=".899" zone="14" spin_dir="209.853" spin_rate="1856.800"  cc="" mt=""/><pitch des="In play, out(s)" id="244" type="X" tfs="161159" tfs_zulu="2012-03-03T21:11:59Z" x="81.55" y="147.65" sv_id="120303_141158" start_speed="89.2" end_speed="82.6" sz_top="3.12" sz_bot="1.54" pfx_x="-9.57" pfx_z="7.13" px="0.623" pz="2.395" x0="-1.889" y0="50.0" z0="6.44" vx0="9.688" vy0="-130.347" vz0="-6.597" ax="-16.55" ay="26.166" az="-19.774" break_y="23.8" break_angle="34.9" break_length="6.0" pitch_type="FT" type_confidence=".903" zone="6" spin_dir="233.157" spin_rate="2301.716"  cc="" mt=""/></atbat><atbat num="29" b="3" s="3" o="2" start_tfs="161230" start_tfs_zulu="2012-03-03T21:12:30Z" batter="446345" stand="R" b_height="6-5" pitcher="119154" p_throws="R" des="Michael Taylor strikes out swinging.  " event="Strikeout"><pitch des="Ball" id="248" type="B" tfs="161243" tfs_zulu="2012-03-03T21:12:43Z" x="68.67" y="168.37" sv_id="120303_141242" start_speed="89.3" end_speed="82.2" sz_top="3.74" sz_bot="1.81" pfx_x="-5.51" pfx_z="6.85" px="1.006" pz="1.332" x0="-1.87" y0="50.0" z0="6.377" vx0="9.223" vy0="-130.363" vz0="-8.997" ax="-9.433" ay="28.508" az="-20.363" break_y="23.8" break_angle="18.7" break_length="5.6" pitch_type="FF" type_confidence=".904" zone="14" spin_dir="218.612" spin_rate="1682.183"  cc="" mt=""/><pitch des="Ball" id="249" type="B" tfs="161257" tfs_zulu="2012-03-03T21:12:57Z" x="69.53" y="170.10" sv_id="120303_141256" start_speed="82.3" end_speed="76.3" sz_top="3.57" sz_bot="1.62" pfx_x="-0.64" pfx_z="0.77" px="0.806" pz="1.562" x0="-2.371" y0="50.0" z0="6.379" vx0="7.739" vy0="-120.425" vz0="-4.918" ax="-0.931" ay="24.078" az="-30.968" break_y="23.8" break_angle="-.7" break_length="8.8" pitch_type="SL" type_confidence=".888" zone="14" spin_dir="217.666" spin_rate="183.545"  cc="" mt=""/><pitch des="Called Strike" id="250" type="S" tfs="161312" tfs_zulu="2012-03-03T21:13:12Z" x="71.24" y="151.10" sv_id="120303_141311" start_speed="89.6" end_speed="82.2" sz_top="3.65" sz_bot="1.73" pfx_x="-9.75" pfx_z="8.87" px="0.858" pz="2.515" x0="-1.939" y0="50.0" z0="6.41" vx0="10.476" vy0="-130.75" vz0="-6.787" ax="-16.826" ay="28.257" az="-16.791" break_y="23.8" break_angle="38.8" break_length="5.5" pitch_type="FT" type_confidence=".904" zone="14" spin_dir="227.564" spin_rate="2529.637"  cc="" mt=""/><pitch des="Swinging Strike" id="251" type="S" tfs="161327" tfs_zulu="2012-03-03T21:13:27Z" x="121.03" y="120.88" sv_id="120303_141326" start_speed="89.2" end_speed="81.8" sz_top="3.55" sz_bot="1.79" pfx_x="-10.35" pfx_z="9.22" px="-0.753" pz="3.723" x0="-2.055" y0="50.0" z0="6.596" vx0="6.81" vy0="-130.643" vz0="-4.242" ax="-17.803" ay="28.72" az="-16.239" break_y="23.8" break_angle="43.6" break_length="5.6" pitch_type="FT" type_confidence=".904" zone="11" spin_dir="228.168" spin_rate="2653.292"  cc="" mt=""/><pitch des="Ball" id="252" type="B" tfs="161345" tfs_zulu="2012-03-03T21:13:45Z" x="80.69" y="201.18" sv_id="120303_141344" start_speed="73.9" end_speed="68.4" sz_top="3.58" sz_bot="1.77" pfx_x="-0.38" pfx_z="-8.32" px="0.693" pz="-0.144" x0="-1.939" y0="50.0" z0="6.513" vx0="5.673" vy0="-108.146" vz0="-4.212" ax="-0.445" ay="22.876" az="-41.723" break_y="23.8" break_angle="-.6" break_length="14.9" pitch_type="CU" type_confidence=".888" zone="14" spin_dir="357.334" spin_rate="1282.392"  cc="" mt=""/><pitch des="Swinging Strike" id="253" type="S" tfs="161405" tfs_zulu="2012-03-03T21:14:05Z" x="106.44" y="158.01" sv_id="120303_141404" start_speed="90.8" end_speed="82.9" sz_top="3.55" sz_bot="1.79" pfx_x="-11.54" pfx_z="5.72" px="-0.127" pz="2.241" x0="-1.867" y0="50.0" z0="6.415" vx0="8.437" vy0="-132.707" vz0="-6.662" ax="-20.338" ay="31.467" az="-22.014" break_y="23.7" break_angle="38.0" break_length="6.9" pitch_type="FT" type_confidence=".906" zone="8" spin_dir="243.455" spin_rate="2485.391"  cc="" mt=""/></atbat><atbat num="30" b="1" s="3" o="3" start_tfs="161423" start_tfs_zulu="2012-03-03T21:14:23Z" batter="489232" stand="R" b_height="6-2" pitcher="119154" p_throws="R" des="Anthony Recker called out on strikes.  " event="Strikeout"><pitch des="Called Strike" id="257" type="S" tfs="161440" tfs_zulu="2012-03-03T21:14:40Z" x="65.24" y="152.83" sv_id="120303_141439" start_speed="90.1" end_speed="82.0" sz_top="3.67" sz_bot="1.64" pfx_x="-4.59" pfx_z="9.71" px="0.998" pz="2.102" x0="-1.811" y0="50.0" z0="6.425" vx0="8.791" vy0="-131.638" vz0="-8.201" ax="-7.942" ay="31.839" az="-15.315" break_y="23.7" break_angle="18.9" break_length="4.3" pitch_type="FF" type_confidence=".900" zone="14" spin_dir="205.223" spin_rate="2053.876"  cc="" mt=""/><pitch des="Called Strike" id="258" type="S" tfs="161455" tfs_zulu="2012-03-03T21:14:55Z" x="112.45" y="151.10" sv_id="120303_141454" start_speed="90.3" end_speed="82.2" sz_top="3.64" sz_bot="1.62" pfx_x="-12.59" pfx_z="6.59" px="-0.498" pz="2.035" x0="-1.856" y0="50.0" z0="6.424" vx0="7.74" vy0="-131.947" vz0="-7.376" ax="-21.869" ay="31.866" az="-20.652" break_y="23.7" break_angle="41.9" break_length="7.0" pitch_type="FT" type_confidence=".905" zone="7" spin_dir="242.216" spin_rate="2717.858"  cc="" mt=""/><pitch des="Ball" id="259" type="B" tfs="161510" tfs_zulu="2012-03-03T21:15:10Z" x="36.91" y="204.64" sv_id="120303_141509" start_speed="74.3" end_speed="69.5" sz_top="3.5" sz_bot="1.57" pfx_x="0.22" pfx_z="-6.59" px="2.025" pz="-1.445" x0="-1.804" y0="50.0" z0="6.317" vx0="8.085" vy0="-108.414" vz0="-7.152" ax="0.259" ay="21.511" az="-39.829" break_y="23.9" break_angle="-1.9" break_length="14.2" pitch_type="CU" type_confidence=".891" zone="14" spin_dir="1.936" spin_rate="1024.968"  cc="" mt=""/><pitch des="Called Strike" id="260" type="S" tfs="161535" tfs_zulu="2012-03-03T21:15:35Z" x="76.39" y="124.34" sv_id="120303_141534" start_speed="90.8" end_speed="82.3" sz_top="3.6" sz_bot="1.68" pfx_x="-9.75" pfx_z="9.36" px="0.716" pz="3.426" x0="-1.717" y0="50.0" z0="6.63" vx0="9.616" vy0="-132.65" vz0="-5.316" ax="-17.104" ay="32.601" az="-15.693" break_y="23.7" break_angle="41.1" break_length="5.2" pitch_type="FT" type_confidence=".905" zone="12" spin_dir="226.062" spin_rate="2597.766"  cc="" mt=""/></atbat></top><bottom><action b="0" s="0" o="0" des="Pitcher Change: Jerry Blevins replaces Jarrod Parker.  " event="Pitching Substitution" tfs="161650" tfs_zulu="2012-03-03T21:16:50Z" player="460283" pitch="4"/><atbat num="31" b="2" s="3" o="1" start_tfs="161754" start_tfs_zulu="2012-03-03T21:17:54Z" batter="455077" stand="L" b_height="6-2" pitcher="460283" p_throws="L" des="Mike Carp strikes out swinging.  " event="Strikeout"><pitch des="Ball" id="267" type="B" tfs="161824" tfs_zulu="2012-03-03T21:18:24Z" x="140.77" y="153.69" sv_id="120303_141824" start_speed="71.8" end_speed="65.9" sz_top="3.07" sz_bot="1.27" pfx_x="-9.33" pfx_z="-4.52" px="-1.305" pz="2.148" x0="2.498" y0="50.0" z0="6.245" vx0="-5.336" vy0="-105.222" vz0="0.589" ax="-10.202" ay="22.039" az="-37.042" break_y="23.8" break_angle="16.7" break_length="14.4" pitch_type="CU" type_confidence=".883" zone="13" spin_dir="295.509" spin_rate="1558.562"  cc="" mt=""/><pitch des="Swinging Strike" id="268" type="S" tfs="161840" tfs_zulu="2012-03-03T21:18:40Z" x="92.70" y="160.60" sv_id="120303_141840" start_speed="90.4" end_speed="82.9" sz_top="3.32" sz_bot="1.47" pfx_x="5.93" pfx_z="9.17" px="0.311" pz="1.89" x0="2.326" y0="50.0" z0="5.922" vx0="-7.251" vy0="-132.228" vz0="-7.431" ax="10.432" ay="29.878" az="-15.961" break_y="23.8" break_angle="-26.7" break_length="4.6" pitch_type="SI" type_confidence=".920" zone="9" spin_dir="147.243" spin_rate="2115.281"  cc="" mt=""/><pitch des="Ball" id="269" type="B" tfs="161857" tfs_zulu="2012-03-03T21:18:57Z" x="107.30" y="183.92" sv_id="120303_141856" start_speed="82.8" end_speed="76.3" sz_top="3.42" sz_bot="1.31" pfx_x="7.93" pfx_z="6.23" px="-0.206" pz="0.847" x0="2.392" y0="50.0" z0="5.613" vx0="-8.646" vy0="-121.011" vz0="-6.559" ax="11.694" ay="24.747" az="-22.902" break_y="23.8" break_angle="-22.6" break_length="7.2" pitch_type="SI" type_confidence=".536" zone="13" spin_dir="128.411" spin_rate="1789.191"  cc="" mt=""/><pitch des="Called Strike" id="270" type="S" tfs="161916" tfs_zulu="2012-03-03T21:19:16Z" x="124.46" y="151.97" sv_id="120303_141915" start_speed="91.5" end_speed="83.6" sz_top="3.26" sz_bot="1.27" pfx_x="5.73" pfx_z="8.86" px="-0.81" pz="2.314" x0="2.061" y0="50.0" z0="5.995" vx0="-9.502" vy0="-133.674" vz0="-6.598" ax="10.27" ay="31.218" az="-16.206" break_y="23.7" break_angle="-24.6" break_length="4.4" pitch_type="SI" type_confidence=".902" zone="11" spin_dir="147.254" spin_rate="2060.524"  cc="" mt=""/><pitch des="Swinging Strike" id="271" type="S" tfs="161933" tfs_zulu="2012-03-03T21:19:33Z" x="132.19" y="166.65" sv_id="120303_141932" start_speed="73.8" end_speed="67.8" sz_top="3.32" sz_bot="1.47" pfx_x="-11.13" pfx_z="0.33" px="-0.924" pz="1.426" x0="2.539" y0="50.0" z0="6.055" vx0="-4.276" vy0="-108.163" vz0="-2.294" ax="-12.888" ay="22.879" az="-31.714" break_y="23.8" break_angle="22.9" break_length="12.3" pitch_type="CU" type_confidence=".688" zone="13" spin_dir="267.956" spin_rate="1729.759"  cc="" mt=""/></atbat><atbat num="32" b="1" s="0" o="2" start_tfs="161947" start_tfs_zulu="2012-03-03T21:19:47Z" batter="400018" stand="R" b_height="6-0" pitcher="460283" p_throws="L" des="Miguel Olivo grounds out to first baseman Kila Ka'aihue.  " event="Groundout"><pitch des="Ball" id="275" type="B" tfs="162007" tfs_zulu="2012-03-03T21:20:07Z" x="29.18" y="126.06" sv_id="120303_142006" start_speed="91.3" end_speed="82.9" sz_top="3.13" sz_bot="1.33" pfx_x="5.07" pfx_z="12.05" px="2.208" pz="3.456" x0="2.502" y0="50.0" z0="6.141" vx0="-2.496" vy0="-133.739" vz0="-5.023" ax="9.043" ay="32.927" az="-10.612" break_y="23.7" break_angle="-35.5" break_length="3.3" pitch_type="SI" type_confidence=".921" zone="12" spin_dir="157.248" spin_rate="2536.396"  cc="" mt=""/><pitch des="In play, out(s)" id="276" type="X" tfs="162023" tfs_zulu="2012-03-03T21:20:23Z" x="57.51" y="148.51" sv_id="120303_142022" start_speed="82.5" end_speed="75.2" sz_top="2.97" sz_bot="1.46" pfx_x="6.81" pfx_z="8.02" px="1.217" pz="2.387" x0="2.601" y0="50.0" z0="5.761" vx0="-5.376" vy0="-120.772" vz0="-3.693" ax="9.926" ay="26.485" az="-20.42" break_y="23.7" break_angle="-22.5" break_length="6.4" pitch_type="SI" type_confidence=".627" zone="12" spin_dir="139.821" spin_rate="1848.071"  cc="" mt=""/></atbat><atbat num="33" b="1" s="0" o="2" start_tfs="162049" start_tfs_zulu="2012-03-03T21:20:49Z" batter="451713" stand="L" b_height="6-5" pitcher="460283" p_throws="L" des="Carlos Peguero homers (1) on a fly ball to right field.  " event="Home Run" score="T" home_team_runs="2" away_team_runs="3"><pitch des="Ball" id="280" type="B" tfs="162102" tfs_zulu="2012-03-03T21:21:02Z" x="86.70" y="170.10" sv_id="120303_142101" start_speed="91.7" end_speed="82.9" sz_top="3.35" sz_bot="1.55" pfx_x="7.01" pfx_z="11.92" px="0.482" pz="1.596" x0="2.298" y0="50.0" z0="5.883" vx0="-7.147" vy0="-134.008" vz0="-9.177" ax="12.494" ay="34.43" az="-10.865" break_y="23.7" break_angle="-39.1" break_length="3.9" pitch_type="SI" type_confidence=".930" zone="9" spin_dir="149.617" spin_rate="2674.226"  cc="" mt=""/><pitch des="In play, run(s)" id="281" type="X" tfs="162118" tfs_zulu="2012-03-03T21:21:18Z" x="86.70" y="146.79" sv_id="120303_142118" start_speed="85.5" end_speed="78.4" sz_top="3.47" sz_bot="1.59" pfx_x="-0.91" pfx_z="8.3" px="0.318" pz="2.518" x0="2.524" y0="50.0" z0="5.955" vx0="-5.142" vy0="-125.218" vz0="-4.603" ax="-1.439" ay="27.292" az="-19.032" break_y="23.8" break_angle="7.1" break_length="5.2" pitch_type="SL" type_confidence=".775" zone="6" spin_dir="186.247" spin_rate="1531.739"  cc="" mt=""/><runner id="451713" start="" end="" event="Home Run" score="T" rbi="T" earned="T"/></atbat><atbat num="34" b="2" s="3" o="3" start_tfs="162155" start_tfs_zulu="2012-03-03T21:21:55Z" batter="459431" stand="L" b_height="6-4" pitcher="460283" p_throws="L" des="Michael Saunders strikes out swinging.  " event="Strikeout"><pitch des="Ball" id="286" type="B" tfs="162211" tfs_zulu="2012-03-03T21:22:11Z" x="66.95" y="170.96" sv_id="120303_142210" start_speed="91.0" end_speed="82.7" sz_top="3.55" sz_bot="1.63" pfx_x="5.96" pfx_z="11.49" px="1.092" pz="1.321" x0="2.359" y0="50.0" z0="5.889" vx0="-5.314" vy0="-132.99" vz0="-9.637" ax="10.494" ay="32.798" az="-11.861" break_y="23.7" break_angle="-33.0" break_length="3.9" pitch_type="SI" type_confidence=".927" zone="14" spin_dir="152.680" spin_rate="2494.175"  cc="" mt=""/><pitch des="Called Strike" id="287" type="S" tfs="162230" tfs_zulu="2012-03-03T21:22:30Z" x="116.74" y="141.61" sv_id="120303_142229" start_speed="90.6" end_speed="81.9" sz_top="3.48" sz_bot="1.53" pfx_x="5.51" pfx_z="12.7" px="-0.589" pz="2.816" x0="2.065" y0="50.0" z0="5.957" vx0="-8.736" vy0="-132.519" vz0="-6.231" ax="9.606" ay="33.516" az="-9.957" break_y="23.7" break_angle="-32.8" break_length="3.2" pitch_type="SI" type_confidence=".897" zone="4" spin_dir="156.619" spin_rate="2649.872"  cc="" mt=""/><pitch des="Ball" id="288" type="B" tfs="162248" tfs_zulu="2012-03-03T21:22:48Z" x="104.72" y="172.69" sv_id="120303_142247" start_speed="82.5" end_speed="75.5" sz_top="3.51" sz_bot="1.45" pfx_x="7.97" pfx_z="5.16" px="-0.071" pz="1.258" x0="2.396" y0="50.0" z0="5.708" vx0="-8.294" vy0="-120.652" vz0="-5.361" ax="11.606" ay="26.124" az="-24.58" break_y="23.8" break_angle="-21.1" break_length="7.7" pitch_type="SI" type_confidence=".438" zone="13" spin_dir="123.198" spin_rate="1667.762"  cc="" mt=""/><pitch des="Foul" id="289" type="S" tfs="162305" tfs_zulu="2012-03-03T21:23:05Z" x="81.55" y="149.38" sv_id="120303_142305" start_speed="89.8" end_speed="82.3" sz_top="3.54" sz_bot="1.75" pfx_x="9.06" pfx_z="7.54" px="0.588" pz="2.498" x0="2.302" y0="50.0" z0="5.942" vx0="-7.479" vy0="-131.424" vz0="-5.245" ax="15.746" ay="29.445" az="-18.989" break_y="23.8" break_angle="-35.1" break_length="5.8" pitch_type="SI" type_confidence=".932" zone="6" spin_dir="129.942" spin_rate="2267.101"  cc="" mt=""/><pitch des="Foul" id="290" type="S" tfs="162327" tfs_zulu="2012-03-03T21:23:27Z" x="109.01" y="135.56" sv_id="120303_142326" start_speed="72.7" end_speed="66.7" sz_top="3.54" sz_bot="1.75" pfx_x="-10.2" pfx_z="-1.91" px="-0.317" pz="3.116" x0="2.521" y0="50.0" z0="6.228" vx0="-3.166" vy0="-106.518" vz0="1.711" ax="-11.505" ay="21.399" az="-34.252" break_y="23.8" break_angle="19.5" break_length="13.0" pitch_type="CU" type_confidence=".849" zone="1" spin_dir="280.238" spin_rate="1592.343"  cc="" mt=""/><pitch des="Swinging Strike" id="291" type="S" tfs="162350" tfs_zulu="2012-03-03T21:23:50Z" x="135.62" y="145.92" sv_id="120303_142349" start_speed="72.6" end_speed="66.6" sz_top="3.54" sz_bot="1.75" pfx_x="-9.9" pfx_z="-2.38" px="-1.0" pz="2.383" x0="2.466" y0="50.0" z0="6.251" vx0="-4.546" vy0="-106.417" vz0="0.302" ax="-11.103" ay="22.061" az="-34.773" break_y="23.8" break_angle="18.9" break_length="13.3" pitch_type="CU" type_confidence=".853" zone="13" spin_dir="283.175" spin_rate="1554.588"  cc="" mt=""/></atbat></bottom></inning>