<!--Copyright 2012 MLB Advanced Media, L.P.  Use of any content on this page acknowledges agreement to the terms posted here http://gdx.mlb.com/components/copyright.txt--><inning num="1" away_team="sfn" home_team="ari" next="Y"><top><atbat num="1" b="0" s="0" o="1" start_tfs="151153" start_tfs_zulu="2012-03-04T20:11:53Z" batter="434636" stand="L" b_height="6-2" pitcher="453178" p_throws="R" des="Angel Pagan lines out to left fielder Gerardo Parra.  " event="Lineout"><pitch des="In play, out(s)" id="3" type="X" tfs="151217" tfs_zulu="2012-03-04T20:12:17Z" x="101.29" y="137.29"  cc="" mt=""/></atbat><atbat num="2" b="0" s="0" o="1" start_tfs="151235" start_tfs_zulu="2012-03-04T20:12:35Z" batter="466320" stand="L" b_height="6-0" pitcher="453178" p_throws="R" des="Melky Cabrera doubles (1) on a line drive to center fielder Chris Young.  " event="Double"><pitch des="In play, no out" id="7" type="X" tfs="151404" tfs_zulu="2012-03-04T20:14:04Z" x="98.71" y="131.24"  cc="" mt=""/><runner id="466320" start="" end="2B" event="Double"/></atbat><atbat num="3" b="0" s="0" o="2" start_tfs="151420" start_tfs_zulu="2012-03-04T20:14:20Z" batter="467055" stand="L" b_height="5-11" pitcher="453178" p_throws="R" des="Pablo Sandoval flies out to left fielder Gerardo Parra.  " event="Flyout"><pitch des="In play, out(s)" id="11" type="X" tfs="151516" tfs_zulu="2012-03-04T20:15:16Z" x="99.57" y="124.34" on_2b="466320"  cc="" mt=""/></atbat><atbat num="4" b="0" s="3" o="3" start_tfs="151527" start_tfs_zulu="2012-03-04T20:15:27Z" batter="333492" stand="L" b_height="6-4" pitcher="453178" p_throws="R" des="Aubrey Huff strikes out swinging.  " event="Strikeout"><pitch des="Swinging Strike" id="15" type="S" tfs="151828" tfs_zulu="2012-03-04T20:18:28Z" x="87.55" y="131.24" on_2b="466320"  cc="" mt=""/><pitch des="Swinging Strike" id="16" type="S" tfs="151830" tfs_zulu="2012-03-04T20:18:30Z" x="90.13" y="131.24" on_2b="466320"  cc="" mt=""/><pitch des="Swinging Strike" id="17" type="S" tfs="151832" tfs_zulu="2012-03-04T20:18:32Z" x="90.13" y="131.24" on_2b="466320"  cc="" mt=""/><runner id="466320" start="2B" end="" event="Strikeout"/></atbat></top><bottom><atbat num="5" b="0" s="3" o="1" start_tfs="152123" start_tfs_zulu="2012-03-04T20:21:23Z" batter="217100" stand="R" b_height="5-11" pitcher="434638" p_throws="L" des="Willie Bloomquist strikes out swinging.  " event="Strikeout"><pitch des="Swinging Strike" id="23" type="S" tfs="152258" tfs_zulu="2012-03-04T20:22:58Z" x="85.84" y="126.06"  cc="" mt=""/><pitch des="Swinging Strike" id="24" type="S" tfs="152302" tfs_zulu="2012-03-04T20:23:02Z" x="85.84" y="126.06"  cc="" mt=""/><pitch des="Swinging Strike" id="25" type="S" tfs="152305" tfs_zulu="2012-03-04T20:23:05Z" x="85.84" y="126.06"  cc="" mt=""/></atbat><atbat num="6" b="0" s="0" o="1" start_tfs="152311" start_tfs_zulu="2012-03-04T20:23:11Z" batter="431094" stand="R" b_height="5-11" pitcher="434638" p_throws="L" des="Aaron Hill doubles (1) on a ground ball to left fielder Melky Cabrera.  " event="Double"><pitch des="In play, no out" id="29" type="X" tfs="152321" tfs_zulu="2012-03-04T20:23:21Z" x="100.43" y="132.97"  cc="" mt=""/><runner id="431094" start="" end="2B" event="Double"/></atbat><atbat num="7" b="0" s="0" o="2" start_tfs="152333" start_tfs_zulu="2012-03-04T20:23:33Z" batter="455759" stand="R" b_height="6-2" pitcher="434638" p_throws="L" des="Chris Young grounds out, third baseman Pablo Sandoval to first baseman Brett Pill.  " event="Groundout"><pitch des="In play, out(s)" id="33" type="X" tfs="152502" tfs_zulu="2012-03-04T20:25:02Z" x="94.42" y="129.52" on_2b="431094"  cc="" mt=""/></atbat><atbat num="8" b="0" s="0" o="3" start_tfs="152512" start_tfs_zulu="2012-03-04T20:25:12Z" batter="471083" stand="L" b_height="5-11" pitcher="434638" p_throws="L" des="Miguel Montero flies out to center fielder Angel Pagan.  " event="Flyout"><pitch des="In play, out(s)" id="37" type="X" tfs="152525" tfs_zulu="2012-03-04T20:25:25Z" x="98.71" y="139.02" on_2b="431094"  cc="" mt=""/><runner id="431094" start="2B" end="" event="Flyout"/></atbat></bottom></inning>