<!--Copyright 2012 MLB Advanced Media, L.P.  Use of any content on this page acknowledges agreement to the terms posted here http://gdx.mlb.com/components/copyright.txt--><hitchart><hip des="Groundout" x="145.58" y="170.68" batter="581640" pitcher="444941" type="O" team="A" inning="1"/><hip des="Flyout" x="181.73" y="102.41" batter="276519" pitcher="596133" type="O" team="H" inning="1"/><hip des="Flyout" x="70.28" y="111.45" batter="425664" pitcher="596133" type="O" team="H" inning="1"/><hip des="Flyout" x="185.74" y="110.44" batter="581532" pitcher="444941" type="O" team="A" inning="2"/><hip des="Flyout" x="123.49" y="87.35" batter="596056" pitcher="444941" type="O" team="A" inning="2"/><hip des="Groundout" x="102.41" y="172.69" batter="421064" pitcher="605282" type="O" team="H" inning="2"/><hip des="Groundout" x="110.44" y="158.63" batter="460055" pitcher="605282" type="O" team="H" inning="2"/><hip des="Groundout" x="112.45" y="159.64" batter="592556" pitcher="518617" type="O" team="A" inning="3"/><hip des="Groundout" x="135.54" y="159.64" batter="492841" pitcher="581642" type="O" team="H" inning="3"/><hip des="Double" x="185.74" y="78.31" batter="488912" pitcher="581642" type="H" team="H" inning="3"/><hip des="Pop Out" x="108.43" y="151.61" batter="334393" pitcher="581642" type="O" team="H" inning="3"/><hip des="Flyout" x="72.29" y="111.45" batter="425664" pitcher="581642" type="O" team="H" inning="3"/><hip des="Groundout" x="112.45" y="157.63" batter="581527" pitcher="456662" type="O" team="A" inning="4"/><hip des="Flyout" x="66.27" y="105.42" batter="581640" pitcher="456662" type="O" team="A" inning="4"/><hip des="Lineout" x="174.70" y="107.43" batter="581532" pitcher="456662" type="O" team="A" inning="4"/><hip des="Double" x="108.43" y="51.20" batter="452254" pitcher="613317" type="H" team="H" inning="4"/><hip des="Groundout" x="140.56" y="158.63" batter="421064" pitcher="613317" type="O" team="H" inning="4"/><hip des="Pop Out" x="105.42" y="148.59" batter="502126" pitcher="613317" type="O" team="H" inning="4"/><hip des="Groundout" x="112.45" y="159.64" batter="460055" pitcher="613317" type="O" team="H" inning="4"/><hip des="Flyout" x="175.70" y="110.44" batter="596056" pitcher="543754" type="O" team="A" inning="5"/><hip des="Flyout" x="121.49" y="82.33" batter="581529" pitcher="543754" type="O" team="A" inning="5"/><hip des="Flyout" x="71.29" y="108.43" batter="595895" pitcher="543754" type="O" team="A" inning="5"/><hip des="Groundout" x="138.55" y="161.65" batter="492841" pitcher="581638" type="O" team="H" inning="5"/><hip des="Flyout" x="173.69" y="105.42" batter="488912" pitcher="581638" type="O" team="H" inning="5"/><hip des="Single" x="118.47" y="148.59" batter="581528" pitcher="456045" type="H" team="A" inning="6"/><hip des="Flyout" x="69.28" y="110.44" batter="592556" pitcher="456045" type="O" team="A" inning="6"/><hip des="Single" x="174.70" y="114.46" batter="582473" pitcher="456045" type="H" team="A" inning="6"/><hip des="Flyout" x="178.71" y="113.45" batter="581527" pitcher="456045" type="O" team="A" inning="6"/><hip des="Single" x="119.48" y="104.42" batter="502265" pitcher="600237" type="H" team="H" inning="6"/><hip des="Single" x="103.41" y="161.65" batter="325392" pitcher="600237" type="H" team="H" inning="6"/><hip des="Groundout" x="107.43" y="171.69" batter="460055" pitcher="600237" type="O" team="H" inning="6"/><hip des="Field Error" x="139.56" y="154.62" batter="581532" pitcher="500724" type="E" team="A" inning="7"/><hip des="Single" x="75.30" y="122.49" batter="596056" pitcher="500724" type="H" team="A" inning="7"/><hip des="Groundout" x="136.55" y="153.61" batter="595895" pitcher="500724" type="O" team="A" inning="7"/><hip des="Groundout" x="105.42" y="173.69" batter="581528" pitcher="500724" type="O" team="A" inning="7"/><hip des="Double" x="185.74" y="80.32" batter="434681" pitcher="600238" type="H" team="H" inning="7"/><hip des="Single" x="72.29" y="116.47" batter="456124" pitcher="600238" type="H" team="H" inning="7"/><hip des="Field Error" x="140.56" y="154.62" batter="520471" pitcher="600238" type="E" team="H" inning="7"/><hip des="Groundout" x="144.58" y="169.68" batter="502265" pitcher="600238" type="O" team="H" inning="7"/><hip des="Pop Out" x="100.40" y="171.69" batter="428642" pitcher="600238" type="O" team="H" inning="7"/><hip des="Home Run" x="55.22" y="60.24" batter="425659" pitcher="600238" type="H" team="H" inning="7"/><hip des="Groundout" x="135.54" y="157.63" batter="325392" pitcher="600238" type="O" team="H" inning="7"/><hip des="Groundout" x="139.56" y="157.63" batter="613364" pitcher="518418" type="O" team="A" inning="8"/><hip des="Single" x="175.70" y="115.46" batter="592603" pitcher="518418" type="H" team="A" inning="8"/><hip des="Groundout" x="137.55" y="153.61" batter="613320" pitcher="518418" type="O" team="A" inning="8"/><hip des="Flyout" x="76.31" y="105.42" batter="435623" pitcher="600232" type="O" team="H" inning="8"/><hip des="Groundout" x="139.56" y="157.63" batter="434681" pitcher="600232" type="O" team="H" inning="8"/><hip des="Groundout" x="108.43" y="156.63" batter="581641" pitcher="543725" type="O" team="A" inning="9"/><hip des="Flyout" x="175.70" y="110.44" batter="596056" pitcher="543725" type="O" team="A" inning="9"/><hip des="Single" x="118.47" y="154.62" batter="595871" pitcher="543725" type="H" team="A" inning="9"/><hip des="Single" x="172.69" y="129.52" batter="613363" pitcher="543725" type="H" team="A" inning="9"/><hip des="Groundout" x="104.42" y="173.69" batter="595895" pitcher="543725" type="O" team="A" inning="9"/></hitchart>