<!--Copyright 2012 MLB Advanced Media, L.P.  Use of any content on this page acknowledges agreement to the terms posted here http://gdx.mlb.com/components/copyright.txt--><Player team="sln" id="500674" pos="P" type="pitcher" first_name="Eduardo" last_name="Sanchez" jersey_number="52" height="5-11" weight="170" bats="R" throws="R" dob="02/16/1989"><season avg=".000" ab="0" hr="0" bb="0" so="0" w="0" l="0" sv="0"/><career avg=".144" ab="97" hr="1" bb="16" so="35" w="3" l="1" sv="5"/><Month des="March" avg=".000" ab="0" hr="0" bb="0" so="0"/><Team des="Home" avg=".000" ab="0" hr="0" bb="0" so="0"/><Empty avg=".000" ab="0" hr="0" bb="0" so="0"/><Men_On avg=".000" ab="0" hr="0" bb="0" so="0"/><RISP avg=".000" ab="0" hr="0" bb="0" so="0"/><Loaded avg=".000" ab="0" hr="0" bb="0" so="0"/><vs_LHB avg=".000" ab="0" hr="0" bb="0" so="0"/><vs_RHB avg=".000" ab="0" hr="0" bb="0" so="0"/><vs_B des="Montz" avg=".000" ab="0" hr="0" bb="0" so="0"/></Player>