<!--Copyright 2012 MLB Advanced Media, L.P.  Use of any content on this page acknowledges agreement to the terms posted here http://gdx.mlb.com/components/copyright.txt--><Player team="sea" id="459431" pos="CF" type="batter" first_name="Michael" last_name="Saunders" jersey_number="55" height="6-4" weight="215" bats="L" throws="R" dob="11/19/1986"><season avg=".200" ab="5" hr="1" rbi="2" ops="1.000"/><career avg=".196" ab="572" hr="12" rbi="45" ops=".569"/><month des="March" avg=".167" ab="6" hr="1" rbi="2" ops=".952"/><Team des="Away" avg=".250" ab="4" hr="1" rbi="2" ops="1.400"/><Empty avg=".000" ab="4" hr="0" rbi="0" ops=".200"/><Men_On avg=".500" ab="2" hr="1" rbi="2" ops="2.500"/><RISP avg="1.000" ab="1" hr="1" rbi="2" ops="5.000"/><Loaded avg=".000" ab="0" hr="0" rbi="0" ops=".000"/><vs_LHP avg=".000" ab="2" hr="0" rbi="0" ops=".000"/><vs_RHP avg=".250" ab="4" hr="1" rbi="2" ops="1.400"/><vs_P des="Spence" avg=".000" ab="0" hr="0" rbi="0" ops=".000"/><atbats><ab inning="3" event="Walk"/><ab inning="4" event="Strikeout"/></atbats></Player>