<!--Copyright 2012 MLB Advanced Media, L.P.  Use of any content on this page acknowledges agreement to the terms posted here http://gdx.mlb.com/components/copyright.txt--><inning num="5" away_team="sfn" home_team="mil" next="Y"><top><action b="0" s="0" o="0" des="Defensive Substitution:  Norichika Aoki replaces left fielder Ryan Braun, batting 3rd, playing left field.  " event="Defensive Sub" tfs="161117" tfs_zulu="2012-03-04T21:11:17Z" player="493114" pitch="1"/><action b="0" s="0" o="0" des="Defensive Substitution:  Taylor Green replaces third baseman Aramis Ramirez, batting 4th, playing third base.  " event="Defensive Sub" tfs="161117" tfs_zulu="2012-03-04T21:11:17Z" player="488919" pitch="1"/><action b="0" s="0" o="0" des="Pitcher Change: John Axford replaces Zack Greinke.  " event="Pitching Substitution" tfs="161117" tfs_zulu="2012-03-04T21:11:17Z" player="446099" pitch="1"/><atbat num="28" b="0" s="0" o="1" start_tfs="161125" start_tfs_zulu="2012-03-04T21:11:25Z" batter="571830" stand="R" b_height="6-1" pitcher="446099" p_throws="R" des="Tommy Joseph grounds out, second baseman Brooks Conrad to first baseman Mat Gamel.  " event="Groundout"><pitch des="In play, out(s)" id="161" type="X" tfs="161224" tfs_zulu="2012-03-04T21:12:24Z" x="96.14" y="141.61"  cc="" mt=""/></atbat><atbat num="29" b="0" s="0" o="1" start_tfs="161233" start_tfs_zulu="2012-03-04T21:12:33Z" batter="543216" stand="L" b_height="6-1" pitcher="446099" p_throws="R" des="Conor Gillaspie singles on a ground ball to right fielder Nyjer Morgan.  " event="Single"><pitch des="In play, no out" id="165" type="X" tfs="161320" tfs_zulu="2012-03-04T21:13:20Z" x="87.55" y="148.51"  cc="" mt=""/><runner id="543216" start="" end="1B" event="Single"/></atbat><atbat num="30" b="0" s="0" o="1" start_tfs="161329" start_tfs_zulu="2012-03-04T21:13:29Z" batter="434630" stand="R" b_height="6-2" pitcher="446099" p_throws="R" des="Eli Whiteside singles on a ground ball to left fielder Norichika Aoki.    Conor Gillaspie to 2nd.  " event="Single"><pitch des="In play, no out" id="169" type="X" tfs="161553" tfs_zulu="2012-03-04T21:15:53Z" x="113.30" y="143.33" on_1b="543216"  cc="" mt=""/><runner id="543216" start="1B" end="2B" event="Single"/><runner id="434630" start="" end="1B" event="Single"/></atbat><atbat num="31" b="0" s="0" o="1" start_tfs="161609" start_tfs_zulu="2012-03-04T21:16:09Z" batter="543063" stand="L" b_height="6-2" pitcher="446099" p_throws="R" des="Brandon Crawford singles on a ground ball to center fielder Carlos Gomez.    Conor Gillaspie scores.    Eli Whiteside to 2nd.  " event="Single" score="T" home_team_runs="1" away_team_runs="1"><pitch des="In play, run(s)" id="174" type="X" tfs="161737" tfs_zulu="2012-03-04T21:17:37Z" x="99.57" y="145.06" on_1b="434630" on_2b="543216"  cc="" mt=""/><runner id="434630" start="1B" end="2B" event="Single"/><runner id="543216" start="2B" end="" event="Single" score="T" rbi="T" earned="T"/><runner id="543063" start="" end="1B" event="Single"/></atbat><atbat num="32" b="0" s="0" o="2" start_tfs="161802" start_tfs_zulu="2012-03-04T21:18:02Z" batter="451629" stand="R" b_height="6-1" pitcher="446099" p_throws="R" des="Justin Christian flies out to right fielder Nyjer Morgan.    Eli Whiteside to 3rd.  " event="Flyout"><pitch des="In play, out(s)" id="182" type="X" tfs="161831" tfs_zulu="2012-03-04T21:18:31Z" x="90.13" y="121.75" on_1b="543063" on_2b="434630"  cc="" mt=""/><runner id="434630" start="2B" end="3B" event="Flyout"/></atbat><atbat num="33" b="0" s="3" o="3" start_tfs="161849" start_tfs_zulu="2012-03-04T21:18:49Z" batter="518502" stand="R" b_height="6-1" pitcher="446099" p_throws="R" des="Gary Brown strikes out swinging.  " event="Strikeout"><pitch des="Called Strike" id="187" type="S" tfs="162053" tfs_zulu="2012-03-04T21:20:53Z" x="106.44" y="117.43" on_1b="543063" on_3b="434630"  cc="" mt=""/><pitch des="Swinging Strike" id="188" type="S" tfs="162055" tfs_zulu="2012-03-04T21:20:55Z" x="84.98" y="129.52" on_1b="543063" on_3b="434630"  cc="" mt=""/><pitch des="Swinging Strike" id="189" type="S" tfs="162102" tfs_zulu="2012-03-04T21:21:02Z" x="107.30" y="150.24" on_1b="543063" on_3b="434630"  cc="" mt=""/><runner id="543063" start="1B" end="" event="Strikeout"/><runner id="434630" start="3B" end="" event="Strikeout"/></atbat></top><bottom><atbat num="34" b="0" s="0" o="0" start_tfs="162114" start_tfs_zulu="2012-03-04T21:21:14Z" batter="451143" stand="L" b_height="6-0" pitcher="400076" p_throws="R" des="Mat Gamel reaches on fielding error by first baseman Brandon Belt.  " event="Field Error" event2="Error"><pitch des="In play, no out" id="195" type="X" tfs="162316" tfs_zulu="2012-03-04T21:23:16Z" x="88.41" y="155.42"  cc="" mt=""/><runner id="451143" start="" end="1B" event="Field Error"/></atbat><atbat num="35" b="0" s="0" o="2" start_tfs="162335" start_tfs_zulu="2012-03-04T21:23:35Z" batter="136460" stand="R" b_height="6-1" pitcher="400076" p_throws="R" des="Alex Gonzalez grounds into double play, shortstop Brandon Crawford to second baseman Emmanuel Burriss to first baseman Brandon Belt.    Mat Gamel out at 2nd.  " event="Grounded Into DP"><pitch des="In play, out(s)" id="200" type="X" tfs="162403" tfs_zulu="2012-03-04T21:24:03Z" x="110.73" y="148.51" on_1b="451143"  cc="" mt=""/><runner id="451143" start="1B" end="" event="Grounded Into DP"/></atbat><atbat num="36" b="0" s="0" o="2" start_tfs="162414" start_tfs_zulu="2012-03-04T21:24:14Z" batter="518960" stand="R" b_height="6-0" pitcher="400076" p_throws="R" des="Jonathan Lucroy singles on a ground ball to left fielder Justin Christian.  " event="Single"><pitch des="In play, no out" id="205" type="X" tfs="162556" tfs_zulu="2012-03-04T21:25:56Z" x="110.73" y="151.97"  cc="" mt=""/><runner id="518960" start="" end="1B" event="Single"/></atbat><atbat num="37" b="0" s="0" o="3" start_tfs="162610" start_tfs_zulu="2012-03-04T21:26:10Z" batter="435459" stand="L" b_height="6-0" pitcher="400076" p_throws="R" des="George Kottaras flies out to left fielder Justin Christian.  " event="Flyout"><pitch des="In play, out(s)" id="209" type="X" tfs="162816" tfs_zulu="2012-03-04T21:28:16Z" x="113.30" y="131.24" on_1b="518960"  cc="" mt=""/><runner id="518960" start="1B" end="" event="Flyout"/></atbat></bottom></inning>