<!--Copyright 2012 MLB Advanced Media, L.P.  Use of any content on this page acknowledges agreement to the terms posted here http://gdx.mlb.com/components/copyright.txt--><Player team="mil" id="136460" pos="SS" type="batter" first_name="Alex" last_name="Gonzalez" jersey_number="11" height="6-1" weight="210" bats="R" throws="R" dob="02/15/1977"><season avg=".000" ab="2" hr="0" rbi="0" ops=".000"/><career avg=".247" ab="5552" hr="152" rbi="665" ops=".690"/><month des="March" avg=".000" ab="5" hr="0" rbi="0" ops=".000"/><Team des="Away" avg=".000" ab="3" hr="0" rbi="0" ops=".000"/><Empty avg=".000" ab="1" hr="0" rbi="0" ops=".000"/><Men_On avg=".000" ab="4" hr="0" rbi="0" ops=".000"/><RISP avg=".000" ab="2" hr="0" rbi="0" ops=".000"/><Loaded avg=".000" ab="0" hr="0" rbi="0" ops=".000"/><vs_LHP avg=".000" ab="3" hr="0" rbi="0" ops=".000"/><vs_RHP avg=".000" ab="2" hr="0" rbi="0" ops=".000"/><vs_P des="Rosin" avg=".000" ab="0" hr="0" rbi="0" ops=".000"/><atbats><ab inning="1" event="Pop Out"/><ab inning="3" event="Pop Out"/><ab inning="6" event="Groundout"/></atbats></Player>