<!--Copyright 2012 MLB Advanced Media, L.P.  Use of any content on this page acknowledges agreement to the terms posted here http://gdx.mlb.com/components/copyright.txt--><Player team="tex" id="443558" pos="RF" type="batter" first_name="Nelson" last_name="Cruz" jersey_number="17" height="6-2" weight="240" bats="R" throws="R" dob="07/01/1980"><season avg=".000" ab="0" r="0" sb="0" hr="0" rbi="0" ops=".000"/><career avg=".270" ab="1893" r="269" sb="52" hr="106" rbi="323" ops=".834"/><month des="March" avg=".500" ab="2" r="0" sb="0" hr="0" rbi="0" ops="1.000"/><Team des="Home" avg=".500" ab="2" r="0" sb="0" hr="0" rbi="0" ops="1.000"/><Empty avg=".500" ab="2" r="0" sb="0" hr="0" rbi="0" ops="1.000"/><Men_On avg=".000" ab="0" r="0" sb="0" hr="0" rbi="0" ops=".000"/><RISP avg=".000" ab="0" r="0" sb="0" hr="0" rbi="0" ops=".000"/><Loaded avg=".000" ab="0" r="0" sb="0" hr="0" rbi="0" ops=".000"/><vs_LHP avg=".000" ab="0" r="0" sb="0" hr="0" rbi="0" ops=".000"/><vs_RHP avg=".500" ab="2" r="0" sb="0" hr="0" rbi="0" ops="1.000"/><vs_P des="Herrera" avg=".000" ab="0" r="0" sb="0" hr="0" rbi="0" ops=".000"/><atbats><ab inning="2" event="Single"/><ab inning="5" event="Pop Out"/></atbats></Player>